merge_functions/__init__.py
merge_functions/exceptions.py
merge_functions/main.py
merge_functions/merge.py
merge_functions/node.py
merge_functions-0.0.10.dist-info/LICENSE
merge_functions-0.0.10.dist-info/METADATA
merge_functions-0.0.10.dist-info/WHEEL
merge_functions-0.0.10.dist-info/entry_points.txt
merge_functions-0.0.10.dist-info/RECORD
