Metadata-Version: 2.1
Name: merge_functions
Version: 0.0.10
Summary: merge functions from other python files
Home-page: https://github.com/idlewith/merge_functions
License: MIT
Author: idlewith
Author-email: newellzhou@163.com
Requires-Python: >=3.9
Classifier: Development Status :: 4 - Beta
Classifier: Environment :: Console
Classifier: Intended Audience :: End Users/Desktop
Classifier: License :: OSI Approved :: MIT License
Classifier: Natural Language :: English
Classifier: Operating System :: OS Independent
Classifier: Programming Language :: Python :: 3
Classifier: Programming Language :: Python :: 3.9
Classifier: Programming Language :: Python :: 3.10
Classifier: Programming Language :: Python :: 3.11
Classifier: Programming Language :: Python :: 3.12
Requires-Dist: black (==23.3.0)
Requires-Dist: isort (>=5.12.0,<6.0.0)
